faereld/__init__.py
faereld/__main__.py
faereld/cli.py
faereld/controller.py
faereld/db.py
faereld/help.py
faereld/input.py
faereld/models.py
faereld/printer.py
faereld/utils.py
faereld/configuration/__init__.py
faereld/configuration/configuration.py
faereld/configuration/defaults.py
faereld/graphs/__init__.py
faereld/graphs/box_plot.py
faereld/graphs/summary_graph.py
faereld/graphs/summary_multigraph.py
faereld/summaries/__init__.py
faereld/summaries/detailed.py
faereld/summaries/empty.py
faereld/summaries/productivity.py
faereld/summaries/projects.py
faereld/summaries/simple.py
faereld-0.1.2.dist-info/LICENSE
faereld-0.1.2.dist-info/METADATA
faereld-0.1.2.dist-info/WHEEL
faereld-0.1.2.dist-info/entry_points.txt
faereld-0.1.2.dist-info/top_level.txt
faereld-0.1.2.dist-info/RECORD
