Metadata-Version: 2.1
Name: faereld
Version: 0.1.2
Summary: Time tracking tool
Home-page: UNKNOWN
Author: Mika Naylor (Autophagy)
Author-email: mail@autophagy.io
License: UNKNOWN
Platform: UNKNOWN
Classifier: Development Status :: 4 - Beta
Classifier: License :: OSI Approved :: MIT License
Classifier: Programming Language :: Python :: 3
Classifier: Programming Language :: Python :: 3.6
Classifier: Programming Language :: Python :: 3.7
Requires-Python: >=3.6
Requires-Dist: PyYAML (==5.1)
Requires-Dist: datarum (==0.5.0)
Requires-Dist: wisdomhord (==0.2.4)
Requires-Dist: numpy (==1.15.0)
Requires-Dist: prompt-toolkit (==1.0.15)
Provides-Extra: testing
Requires-Dist: black (==18.9b0) ; extra == 'testing'
Requires-Dist: flake8 (==3.7.7) ; extra == 'testing'
Requires-Dist: mypy (==0.670) ; extra == 'testing'
Requires-Dist: isort (==4.3.15) ; extra == 'testing'
